django_rewrite_external_links-1.1.0.dist-info/DESCRIPTION.rst
django_rewrite_external_links-1.1.0.dist-info/METADATA
django_rewrite_external_links-1.1.0.dist-info/RECORD
django_rewrite_external_links-1.1.0.dist-info/WHEEL
django_rewrite_external_links-1.1.0.dist-info/metadata.json
django_rewrite_external_links-1.1.0.dist-info/top_level.txt
rewrite_external_links/__init__.py
rewrite_external_links/middleware.py
rewrite_external_links/urls.py
rewrite_external_links/views.py
rewrite_external_links/templates/rewrite_external_links/_links.html
rewrite_external_links/templates/rewrite_external_links/external_link.html
rewrite_external_links/templates/rewrite_external_links/external_link_ajax.html
