Metadata-Version: 2.0
Name: django-rewrite-external-links
Version: 1.1.0
Summary: Rewrite all external (off-site) links to go via a message page, using a middleware class.
Home-page: https://github.com/incuna/django-rewrite-external-links
Author: Incuna Ltd
Author-email: admin@incuna.com
License: UNKNOWN
Platform: UNKNOWN
